bol/__init__.py
bol/data/__init__.py
bol/data/wav2vec2/__init__.py
bol/data/wav2vec2/_wav2vec2_fairseq_dataloader.py
bol/data/wav2vec2/_wav2vec2_ts_dataloader.py
bol/inference/__init__.py
bol/inference/_vad_for_long_audios.py
bol/inference/decoders/__init__.py
bol/inference/decoders/_wav2vec2_decoder.py
bol/inference/wav2vec2_fairseq/__init__.py
bol/inference/wav2vec2_fairseq/_wav2vec2_infer_batch.py
bol/inference/wav2vec2_fairseq/_wav2vec2_infer_single.py
bol/metrics/__init__.py
bol/metrics/calculate_metrics.py
bol/metrics/cer.py
bol/metrics/wer.py
bol/models/__init__.py
bol/models/_load_model.py
bol/models/_model.py
bol/models/wav2vec2/__init__.py
bol/models/wav2vec2/_wav2vec2_fairseq.py
bol/models/wav2vec2/_wav2vec2_ts.py
bol/utils/__init__.py
bol/utils/constants.py
bol/utils/helper_functions.py
bol/utils/model_zoo.py
bol/utils/resampler.py
bol/utils/file_operations/__init__.py
bol/utils/file_operations/file_ops.py
bol_library-0.1.8.dist-info/LICENSE
bol_library-0.1.8.dist-info/METADATA
bol_library-0.1.8.dist-info/WHEEL
bol_library-0.1.8.dist-info/top_level.txt
bol_library-0.1.8.dist-info/RECORD
